python_flux/__init__.py
python_flux/flux.py
python_flux/flux_utilis.py
python_flux/producers.py
python_flux/subscribers.py
python_flux-2.0.0.dist-info/METADATA
python_flux-2.0.0.dist-info/WHEEL
python_flux-2.0.0.dist-info/RECORD
