Metadata-Version: 2.1
Name: python-flux
Version: 2.0.0
Summary: Librería que utiliza generadores de python para simular procesamiento de flujo de datos
License: GPL-3.0-or-later
Author: Juan Pablo Bochard
Author-email: jbochard@gmail.com
Requires-Python: >=3.8,<4.0
Classifier: License :: OSI Approved :: GNU General Public License v3 or later (GPLv3+)
Classifier: Programming Language :: Python :: 3
Classifier: Programming Language :: Python :: 3.8
Classifier: Programming Language :: Python :: 3.9
Classifier: Programming Language :: Python :: 3.10
Classifier: Programming Language :: Python :: 3.11
Classifier: Programming Language :: Python :: 3.8
Requires-Dist: jsonmerge (>=1.8,<2.0)
